biostarPython/Log Events.py
biostarPython/__init__.py
biostarPython/event_code.json
biostarPython/proto/access.proto
biostarPython/proto/action.proto
biostarPython/proto/admin.proto
biostarPython/proto/apb_zone.proto
biostarPython/proto/auth.proto
biostarPython/proto/card.proto
biostarPython/proto/cert.proto
biostarPython/proto/config.proto
biostarPython/proto/connect.proto
biostarPython/proto/connect_master.proto
biostarPython/proto/device.proto
biostarPython/proto/devicelicense.proto
biostarPython/proto/display.proto
biostarPython/proto/door.proto
biostarPython/proto/err.proto
biostarPython/proto/error.proto
biostarPython/proto/event.proto
biostarPython/proto/face.proto
biostarPython/proto/finger.proto
biostarPython/proto/fingerprint.proto
biostarPython/proto/fire_zone.proto
biostarPython/proto/gateway.proto
biostarPython/proto/input.proto
biostarPython/proto/interlock_zone.proto
biostarPython/proto/intrusion_zone.proto
biostarPython/proto/lift.proto
biostarPython/proto/lift_zone.proto
biostarPython/proto/lock_zone.proto
biostarPython/proto/login.proto
biostarPython/proto/master.proto
biostarPython/proto/masteradmin.proto
biostarPython/proto/network.proto
biostarPython/proto/operator.proto
biostarPython/proto/rs485.proto
biostarPython/proto/rtsp.proto
biostarPython/proto/schedule.proto
biostarPython/proto/server.proto
biostarPython/proto/status.proto
biostarPython/proto/system.proto
biostarPython/proto/tenant.proto
biostarPython/proto/test.proto
biostarPython/proto/thermal.proto
biostarPython/proto/time.proto
biostarPython/proto/timed_apb_zone.proto
biostarPython/proto/tna.proto
biostarPython/proto/udp.proto
biostarPython/proto/udp_master.proto
biostarPython/proto/user.proto
biostarPython/proto/voip.proto
biostarPython/proto/wiegand.proto
biostarPython/proto/zone.proto
biostarPython/service/access_pb2.py
biostarPython/service/access_pb2_grpc.py
biostarPython/service/action_pb2.py
biostarPython/service/action_pb2_grpc.py
biostarPython/service/admin_pb2.py
biostarpython-0.6.0.0.dist-info/licenses/LICENSE
biostarpython-0.6.0.0.dist-info/METADATA
biostarpython-0.6.0.0.dist-info/WHEEL
biostarpython-0.6.0.0.dist-info/top_level.txt
biostarpython-0.6.0.0.dist-info/RECORD
