Metadata-Version: 2.4
Name: biostarPython
Version: 0.6.0.0
Summary: Python client for Suprema GSDK with included callable classes.
Home-page: https://github.com/gcartlidge/biostarPython
Author: SupremaUK
Author-email: gcartlidge@supremainc.com
Classifier: License :: OSI Approved :: MIT License
Classifier: Programming Language :: Python :: 3
Classifier: Programming Language :: Python :: 3.10
Classifier: Programming Language :: Python :: 3.11
Classifier: Programming Language :: Python :: 3.12
Classifier: Programming Language :: Python :: 3.13
Requires-Python: >3.5.2
License-File: LICENSE
Requires-Dist: grpcio
Requires-Dist: protobuf
Dynamic: author
Dynamic: author-email
Dynamic: classifier
Dynamic: description
Dynamic: description-content-type
Dynamic: home-page
Dynamic: license-file
Dynamic: requires-dist
Dynamic: requires-python
Dynamic: summary
